gptq_triton/__init__.py
gptq_triton/custom_autotune.py
gptq_triton/fused_attention.py
gptq_triton/fused_mlp.py
gptq_triton/quant_linear.py
gptq_triton/utils.py
gptq_triton-0.0.4.dist-info/LICENSE
gptq_triton-0.0.4.dist-info/METADATA
gptq_triton-0.0.4.dist-info/WHEEL
gptq_triton-0.0.4.dist-info/top_level.txt
gptq_triton-0.0.4.dist-info/RECORD
