Metadata-Version: 2.1
Name: gptq-triton
Version: 0.0.4
Summary: Fast GPTQ kernels written in Triton
Home-page: https://github.com/fpgaminer/GPTQ-triton
Author: fpgaminer
Author-email: fpgaminer@bitcoin-mining.com
License: Apache License 2.0
Keywords: gptq,triton,torch,cuda,gpu,quantization,quantize,quantized,inference,deep learning,machine learning
Classifier: Development Status :: 3 - Alpha
Classifier: License :: OSI Approved :: Apache Software License
Classifier: Intended Audience :: Developers
Classifier: Programming Language :: Python :: 3
Classifier: Programming Language :: Python :: 3.6
Classifier: Programming Language :: Python :: 3.7
Classifier: Programming Language :: Python :: 3.8
Classifier: Programming Language :: Python :: 3.9
Classifier: Programming Language :: Python :: 3.10
Classifier: Topic :: Scientific/Engineering :: Artificial Intelligence
Classifier: Topic :: Software Development :: Libraries :: Python Modules
Requires-Python: >=3.6
License-File: LICENSE
Requires-Dist: triton (>=2.0.0)
Requires-Dist: torch (>=2.0.0)
Requires-Dist: transformers
